_libe1.cpython-312-x86_64-linux-musl.so
e1.py
e1-0.2.1.dist-info/METADATA
e1-0.2.1.dist-info/WHEEL
e1-0.2.1.dist-info/top_level.txt
e1-0.2.1.dist-info/RECORD
e1-0.2.1.dist-info/licenses/AUTHORS.rst
e1-0.2.1.dist-info/licenses/LICENSE.txt
