Metadata-Version: 2.1
Name: e1
Version: 0.2.1
Summary: Python support for the e1 compression format.
Home-page: https://github.com/LANL-seismoacoustics/e1
Download-URL: https://github.com/LANL-seismoacoustics/e1/tarball/0.1.0
Author: Jonathan MacCarthy
Author-email: jkmacc@lanl.gov
License: MIT
Keywords: seismology,geophysics
Platform: Mac OS X
Platform: Linux/Unix
License-File: LICENSE.txt
License-File: AUTHORS.rst
Requires-Dist: numpy
